[
  {
    "순위": "1",
    "길드": "나혼렙갤러리",
    "닉네임": "2line",
    "점수": "150,498,227,702",
    "격노": "175",
    "_originalRowNumber": 9
  },
  {
    "순위": "2",
    "길드": "나혼렙갤러리",
    "닉네임": "SHIN",
    "점수": "149,492,261,582",
    "격노": "174",
    "_originalRowNumber": 10
  },
  {
    "순위": "3",
    "길드": "나혼렙갤러리",
    "닉네임": "그르르",
    "점수": "134,245,819,862",
    "격노": "174",
    "_originalRowNumber": 11
  },
  {
    "순위": "4",
    "길드": "나혼렙갤러리",
    "닉네임": "별똥별",
    "점수": "131,807,147,455",
    "격노": "174",
    "_originalRowNumber": 12
  },
  {
    "순위": "5",
    "길드": "나혼렙갤러리",
    "닉네임": "무야",
    "점수": "150,497,347,793",
    "격노": "173",
    "_originalRowNumber": 13
  },
  {
    "순위": "6",
    "길드": "나혼렙갤러리",
    "닉네임": "심슨",
    "점수": "131,406,778,723",
    "격노": "173",
    "_originalRowNumber": 14
  },
  {
    "순위": "7",
    "길드": "나혼렙갤러리",
    "닉네임": "둘영",
    "점수": "150,279,165,200",
    "격노": "172",
    "_originalRowNumber": 15
  },
  {
    "순위": "8",
    "길드": "나혼렙갤러리",
    "닉네임": "추천",
    "점수": "140,594,310,831",
    "격노": "172",
    "_originalRowNumber": 16
  },
  {
    "순위": "9",
    "길드": "나혼렙갤러리",
    "닉네임": "Gr8",
    "점수": "128,156,963,771",
    "격노": "172",
    "_originalRowNumber": 17
  },
  {
    "순위": "10",
    "길드": "나혼렙갤러리",
    "닉네임": "Dark",
    "점수": "126,714,793,079",
    "격노": "172",
    "_originalRowNumber": 18
  },
  {
    "순위": "11",
    "길드": "나혼렙갤러리",
    "닉네임": "우주최강스타킹",
    "점수": "125,863,004,927",
    "격노": "172",
    "_originalRowNumber": 19
  },
  {
    "순위": "12",
    "길드": "나혼렙갤러리",
    "닉네임": "Meta7",
    "점수": "126,632,595,009",
    "격노": "171",
    "_originalRowNumber": 20
  },
  {
    "순위": "13",
    "길드": "나혼렙갤러리",
    "닉네임": "오쇼",
    "점수": "123,455,410,385",
    "격노": "171",
    "_originalRowNumber": 21
  },
  {
    "순위": "14",
    "길드": "나혼렙갤러리",
    "닉네임": "ᴠᴀʟᴇʀɪᴇ",
    "점수": "123,238,627,967",
    "격노": "171",
    "_originalRowNumber": 22
  },
  {
    "순위": "15",
    "길드": "나혼렙갤러리",
    "닉네임": "절두",
    "점수": "123,075,519,483",
    "격노": "170",
    "_originalRowNumber": 23
  },
  {
    "순위": "16",
    "길드": "나혼렙갤러리",
    "닉네임": "똥맨",
    "점수": "121,663,505,949",
    "격노": "170",
    "_originalRowNumber": 24
  },
  {
    "순위": "17",
    "길드": "나혼렙갤러리",
    "닉네임": "쭈니e",
    "점수": "120,681,837,636",
    "격노": "170",
    "_originalRowNumber": 25
  },
  {
    "순위": "18",
    "길드": "나혼렙갤러리",
    "닉네임": "묵직한주먹",
    "점수": "119,428,751,008",
    "격노": "170",
    "_originalRowNumber": 26
  },
  {
    "순위": "19",
    "길드": "나혼렙갤러리",
    "닉네임": "Dawn",
    "점수": "118,311,010,939",
    "격노": "170",
    "_originalRowNumber": 27
  },
  {
    "순위": "20",
    "길드": "나혼렙갤러리",
    "닉네임": "OhReung",
    "점수": "118,083,134,666",
    "격노": "170",
    "_originalRowNumber": 28
  },
  {
    "순위": "21",
    "길드": "나혼렙갤러리",
    "닉네임": "우주최강귀요미",
    "점수": "132,051,306,410",
    "격노": "169",
    "_originalRowNumber": 29
  },
  {
    "순위": "22",
    "길드": "나혼렙갤러리",
    "닉네임": "Shubel",
    "점수": "131,896,025,269",
    "격노": "169",
    "_originalRowNumber": 30
  },
  {
    "순위": "23",
    "길드": "나혼렙갤러리",
    "닉네임": "shamblez",
    "점수": "116,346,592,609",
    "격노": "169",
    "_originalRowNumber": 31
  },
  {
    "순위": "24",
    "길드": "나혼렙갤러리",
    "닉네임": "김소진",
    "점수": "130,474,049,886",
    "격노": "168",
    "_originalRowNumber": 32
  },
  {
    "순위": "25",
    "길드": "나혼렙갤러리",
    "닉네임": "44khz",
    "점수": "116,221,358,746",
    "격노": "168",
    "_originalRowNumber": 33
  },
  {
    "순위": "26",
    "길드": "ARISE",
    "닉네임": "성일환",
    "점수": "116,016,698,450",
    "격노": "168",
    "_originalRowNumber": 34
  },
  {
    "순위": "27",
    "길드": "나혼렙갤러리",
    "닉네임": "소월",
    "점수": "113,786,081,393",
    "격노": "168",
    "_originalRowNumber": 35
  },
  {
    "순위": "28",
    "길드": "나혼렙갤러리",
    "닉네임": "오리옌테이션",
    "점수": "112,348,636,440",
    "격노": "168",
    "_originalRowNumber": 36
  },
  {
    "순위": "29",
    "길드": "나혼렙갤러리",
    "닉네임": "Rock",
    "점수": "125,572,350,546",
    "격노": "167",
    "_originalRowNumber": 37
  },
  {
    "순위": "30",
    "길드": "나혼렙갤러리",
    "닉네임": "stony",
    "점수": "113,889,253,068",
    "격노": "167",
    "_originalRowNumber": 38
  },
  {
    "순위": "31",
    "길드": "나혼렙갤러리",
    "닉네임": "GOLD",
    "점수": "113,117,715,768",
    "격노": "167",
    "_originalRowNumber": 39
  },
  {
    "순위": "32",
    "길드": "나혼렙갤러리",
    "닉네임": "배추",
    "점수": "112,767,676,376",
    "격노": "167",
    "_originalRowNumber": 40
  },
  {
    "순위": "33",
    "길드": "ARISE",
    "닉네임": "듀란트",
    "점수": "111,582,080,203",
    "격노": "167",
    "_originalRowNumber": 41
  },
  {
    "순위": "34",
    "길드": "나혼렙갤러리",
    "닉네임": "허픽",
    "점수": "124,619,587,114",
    "격노": "166",
    "_originalRowNumber": 42
  },
  {
    "순위": "35",
    "길드": "나혼렙갤러리",
    "닉네임": "HSkM",
    "점수": "110,471,572,524",
    "격노": "166",
    "_originalRowNumber": 43
  },
  {
    "순위": "36",
    "길드": "나혼렙갤러리",
    "닉네임": "YF",
    "점수": "109,843,114,476",
    "격노": "166",
    "_originalRowNumber": 44
  },
  {
    "순위": "37",
    "길드": "나혼렙갤러리",
    "닉네임": "Goo",
    "점수": "109,472,777,473",
    "격노": "166",
    "_originalRowNumber": 45
  },
  {
    "순위": "38",
    "길드": "나혼렙갤러리",
    "닉네임": "베티",
    "점수": "108,911,600,973",
    "격노": "166",
    "_originalRowNumber": 46
  },
  {
    "순위": "39",
    "길드": "나혼렙갤러리",
    "닉네임": "귀신",
    "점수": "108,890,054,774",
    "격노": "166",
    "_originalRowNumber": 47
  },
  {
    "순위": "40",
    "길드": "나혼렙갤러리",
    "닉네임": "오태식",
    "점수": "108,523,611,047",
    "격노": "166",
    "_originalRowNumber": 48
  },
  {
    "순위": "41",
    "길드": "ARISE",
    "닉네임": "슛도리",
    "점수": "107,715,580,571",
    "격노": "166",
    "_originalRowNumber": 49
  },
  {
    "순위": "42",
    "길드": "나혼렙갤러리",
    "닉네임": "AwPSoul",
    "점수": "114,065,223,568",
    "격노": "165",
    "_originalRowNumber": 50
  },
  {
    "순위": "43",
    "길드": "ARISE",
    "닉네임": "마에스트로",
    "점수": "106,844,318,594",
    "격노": "165",
    "_originalRowNumber": 51
  },
  {
    "순위": "44",
    "길드": "나혼렙갤러리",
    "닉네임": "RYUI",
    "점수": "117,575,690,574",
    "격노": "164",
    "_originalRowNumber": 52
  },
  {
    "순위": "45",
    "길드": "나혼렙갤러리",
    "닉네임": "Bon7",
    "점수": "113,695,631,279",
    "격노": "164",
    "_originalRowNumber": 53
  },
  {
    "순위": "46",
    "길드": "나혼렙갤러리",
    "닉네임": "지누",
    "점수": "103,604,777,888",
    "격노": "164",
    "_originalRowNumber": 54
  },
  {
    "순위": "47",
    "길드": "나혼렙갤러리",
    "닉네임": "만두",
    "점수": "101,365,122,315",
    "격노": "164",
    "_originalRowNumber": 55
  },
  {
    "순위": "48",
    "길드": "ARISE",
    "닉네임": "전투경찰순경",
    "점수": "100,949,345,111",
    "격노": "163",
    "_originalRowNumber": 56
  },
  {
    "순위": "49",
    "길드": "나혼렙갤러리",
    "닉네임": "띵박",
    "점수": "100,795,347,870",
    "격노": "163",
    "_originalRowNumber": 57
  },
  {
    "순위": "50",
    "길드": "나혼렙갤러리",
    "닉네임": "푸쉬팝",
    "점수": "100,756,613,567",
    "격노": "163",
    "_originalRowNumber": 58
  },
  {
    "순위": "51",
    "길드": "나혼렙갤러리",
    "닉네임": "여미",
    "점수": "100,206,742,483",
    "격노": "163",
    "_originalRowNumber": 59
  },
  {
    "순위": "52",
    "길드": "ARISE",
    "닉네임": "미도구름",
    "점수": "100,374,354,443",
    "격노": "162",
    "_originalRowNumber": 60
  },
  {
    "순위": "53",
    "길드": "ARISE",
    "닉네임": "고우닝",
    "점수": "98,851,743,204",
    "격노": "162",
    "_originalRowNumber": 61
  },
  {
    "순위": "54",
    "길드": "ARISE",
    "닉네임": "오렌지밀크",
    "점수": "98,666,205,699",
    "격노": "162",
    "_originalRowNumber": 62
  },
  {
    "순위": "55",
    "길드": "나혼렙갤러리",
    "닉네임": "국민학교졸업생",
    "점수": "98,167,112,414",
    "격노": "162",
    "_originalRowNumber": 63
  },
  {
    "순위": "56",
    "길드": "ARISE",
    "닉네임": "구강외과전문의",
    "점수": "97,452,186,616",
    "격노": "162",
    "_originalRowNumber": 64
  },
  {
    "순위": "57",
    "길드": "나혼렙갤러리",
    "닉네임": "하츄",
    "점수": "96,990,056,272",
    "격노": "162",
    "_originalRowNumber": 65
  },
  {
    "순위": "58",
    "길드": "ARISE",
    "닉네임": "사신",
    "점수": "98,015,977,109",
    "격노": "161",
    "_originalRowNumber": 66
  },
  {
    "순위": "59",
    "길드": "ARISE",
    "닉네임": "JUN",
    "점수": "96,673,595,567",
    "격노": "161",
    "_originalRowNumber": 67
  },
  {
    "순위": "60",
    "길드": "ARISE",
    "닉네임": "에스페란서",
    "점수": "96,016,186,590",
    "격노": "161",
    "_originalRowNumber": 68
  },
  {
    "순위": "61",
    "길드": "ARISE",
    "닉네임": "아야러아",
    "점수": "95,772,730,829",
    "격노": "161",
    "_originalRowNumber": 69
  },
  {
    "순위": "62",
    "길드": "나혼렙갤러리",
    "닉네임": "Ayaya",
    "점수": "95,064,189,256",
    "격노": "161",
    "_originalRowNumber": 70
  },
  {
    "순위": "63",
    "길드": "ARISE",
    "닉네임": "월용이",
    "점수": "106,363,315,508",
    "격노": "160",
    "_originalRowNumber": 71
  },
  {
    "순위": "64",
    "길드": "ARISE",
    "닉네임": "않됀다",
    "점수": "100,584,753,640",
    "격노": "160",
    "_originalRowNumber": 72
  },
  {
    "순위": "65",
    "길드": "NTR",
    "닉네임": "성진우",
    "점수": "95,518,424,768",
    "격노": "160",
    "_originalRowNumber": 73
  },
  {
    "순위": "66",
    "길드": "ARISE",
    "닉네임": "냐폴레옹",
    "점수": "93,639,838,755",
    "격노": "160",
    "_originalRowNumber": 74
  },
  {
    "순위": "67",
    "길드": "ARISE",
    "닉네임": "atom",
    "점수": "92,440,125,567",
    "격노": "160",
    "_originalRowNumber": 75
  },
  {
    "순위": "68",
    "길드": "ARISE",
    "닉네임": "암살자",
    "점수": "92,084,239,349",
    "격노": "160",
    "_originalRowNumber": 76
  },
  {
    "순위": "69",
    "길드": "ARISE",
    "닉네임": "otani",
    "점수": "91,830,036,566",
    "격노": "160",
    "_originalRowNumber": 77
  },
  {
    "순위": "70",
    "길드": "아이유",
    "닉네임": "할래",
    "점수": "",
    "격노": "160",
    "_originalRowNumber": 78
  },
  {
    "순위": "71",
    "길드": "ARISE",
    "닉네임": "베르",
    "점수": "90,678,109,739",
    "격노": "159",
    "_originalRowNumber": 79
  },
  {
    "순위": "72",
    "길드": "ARISE",
    "닉네임": "코찔찔이",
    "점수": "89,944,408,537",
    "격노": "159",
    "_originalRowNumber": 80
  },
  {
    "순위": "73",
    "길드": "나혼렙갤러리",
    "닉네임": "김불빛",
    "점수": "89,433,157,875",
    "격노": "159",
    "_originalRowNumber": 81
  },
  {
    "순위": "74",
    "길드": "ARISE",
    "닉네임": "Ethan",
    "점수": "100,395,036,350",
    "격노": "158",
    "_originalRowNumber": 82
  },
  {
    "순위": "75",
    "길드": "ARISE",
    "닉네임": "카이",
    "점수": "90,070,669,398",
    "격노": "158",
    "_originalRowNumber": 83
  },
  {
    "순위": "76",
    "길드": "ARISE",
    "닉네임": "꽁쥐맨",
    "점수": "88,831,127,546",
    "격노": "158",
    "_originalRowNumber": 84
  },
  {
    "순위": "77",
    "길드": "ARISE",
    "닉네임": "웰치스포도맛",
    "점수": "87,540,504,408",
    "격노": "158",
    "_originalRowNumber": 85
  },
  {
    "순위": "78",
    "길드": "ARISE",
    "닉네임": "Shiro",
    "점수": "86,034,668,113",
    "격노": "157",
    "_originalRowNumber": 86
  },
  {
    "순위": "79",
    "길드": "ARISE",
    "닉네임": "연어",
    "점수": "85,879,716,891",
    "격노": "157",
    "_originalRowNumber": 87
  },
  {
    "순위": "80",
    "길드": "ARISE",
    "닉네임": "ursa",
    "점수": "85,397,000,652",
    "격노": "157",
    "_originalRowNumber": 88
  },
  {
    "순위": "81",
    "길드": "ARISE",
    "닉네임": "Sup",
    "점수": "85,396,668,509",
    "격노": "157",
    "_originalRowNumber": 89
  },
  {
    "순위": "82",
    "길드": "NTR",
    "닉네임": "홈랜더",
    "점수": "83,494,110,192",
    "격노": "156",
    "_originalRowNumber": 90
  },
  {
    "순위": "83",
    "길드": "ARISE",
    "닉네임": "마늘이",
    "점수": "82,543,598,222",
    "격노": "156",
    "_originalRowNumber": 91
  },
  {
    "순위": "84",
    "길드": "ARISE",
    "닉네임": "Rekz",
    "점수": "82,314,200,471",
    "격노": "156",
    "_originalRowNumber": 92
  },
  {
    "순위": "85",
    "길드": "ARISE",
    "닉네임": "성수호",
    "점수": "81,940,524,539",
    "격노": "156",
    "_originalRowNumber": 93
  },
  {
    "순위": "86",
    "길드": "NTR",
    "닉네임": "삼체",
    "점수": "81,681,027,584",
    "격노": "156",
    "_originalRowNumber": 94
  },
  {
    "순위": "87",
    "길드": "ARISE",
    "닉네임": "BBAI",
    "점수": "91,956,168,430",
    "격노": "155",
    "_originalRowNumber": 95
  },
  {
    "순위": "88",
    "길드": "ARISE",
    "닉네임": "아수라",
    "점수": "82,503,512,521",
    "격노": "155",
    "_originalRowNumber": 96
  },
  {
    "순위": "89",
    "길드": "ARISE",
    "닉네임": "신비한녀석",
    "점수": "77,751,637,649",
    "격노": "155",
    "_originalRowNumber": 97
  },
  {
    "순위": "90",
    "길드": "NTR",
    "닉네임": "LAPHROAIG",
    "점수": "80,209,442,041",
    "격노": "154",
    "_originalRowNumber": 98
  },
  {
    "순위": "91",
    "길드": "ARISE",
    "닉네임": "성진우",
    "점수": "79,745,579,772",
    "격노": "154",
    "_originalRowNumber": 99
  },
  {
    "순위": "92",
    "길드": "NTR",
    "닉네임": "Manhole",
    "점수": "79,074,609,711",
    "격노": "154",
    "_originalRowNumber": 100
  },
  {
    "순위": "93",
    "길드": "ARISE",
    "닉네임": "당근이",
    "점수": "77,548,868,538",
    "격노": "154",
    "_originalRowNumber": 101
  },
  {
    "순위": "94",
    "길드": "ARISE",
    "닉네임": "거인",
    "점수": "75,535,868,421",
    "격노": "153",
    "_originalRowNumber": 102
  },
  {
    "순위": "95",
    "길드": "NTR",
    "닉네임": "라엘코드",
    "점수": "75,351,774,166",
    "격노": "153",
    "_originalRowNumber": 103
  },
  {
    "순위": "96",
    "길드": "ARISE",
    "닉네임": "뿌꾸",
    "점수": "74,676,298,841",
    "격노": "153",
    "_originalRowNumber": 104
  },
  {
    "순위": "97",
    "길드": "ARISE",
    "닉네임": "교상",
    "점수": "75,001,671,465",
    "격노": "152",
    "_originalRowNumber": 105
  },
  {
    "순위": "98",
    "길드": "NTR",
    "닉네임": "로니",
    "점수": "73,983,247,782",
    "격노": "152",
    "_originalRowNumber": 106
  },
  {
    "순위": "99",
    "길드": "ARISE",
    "닉네임": "ShootDoRi",
    "점수": "73,796,876,167",
    "격노": "151",
    "_originalRowNumber": 107
  },
  {
    "순위": "100",
    "길드": "NTR",
    "닉네임": "나어즈",
    "점수": "72,275,604,647",
    "격노": "151",
    "_originalRowNumber": 108
  },
  {
    "순위": "101",
    "길드": "미레이",
    "닉네임": "디지리",
    "점수": "72,759,013,015",
    "격노": "150",
    "_originalRowNumber": 109
  },
  {
    "순위": "102",
    "길드": "NTR",
    "닉네임": "전설",
    "점수": "70,876,537,135",
    "격노": "150",
    "_originalRowNumber": 110
  },
  {
    "순위": "103",
    "길드": "ARISE",
    "닉네임": "아스본",
    "점수": "66,273,418,327",
    "격노": "149",
    "_originalRowNumber": 111
  },
  {
    "순위": "104",
    "길드": "아이유",
    "닉네임": "앵터",
    "점수": "",
    "격노": "149",
    "_originalRowNumber": 112
  },
  {
    "순위": "105",
    "길드": "NTR",
    "닉네임": "Koala",
    "점수": "65,135,364,064",
    "격노": "148",
    "_originalRowNumber": 113
  },
  {
    "순위": "106",
    "길드": "NTR",
    "닉네임": "유채민",
    "점수": "67,302,738,168",
    "격노": "147",
    "_originalRowNumber": 114
  },
  {
    "순위": "107",
    "길드": "NTR",
    "닉네임": "군주",
    "점수": "61,539,786,247",
    "격노": "147",
    "_originalRowNumber": 115
  },
  {
    "순위": "108",
    "길드": "아이유",
    "닉네임": "Hunter28166780",
    "점수": "",
    "격노": "147",
    "_originalRowNumber": 116
  },
  {
    "순위": "109",
    "길드": "아이유",
    "닉네임": "제롬",
    "점수": "",
    "격노": "147",
    "_originalRowNumber": 117
  },
  {
    "순위": "110",
    "길드": "아이유",
    "닉네임": "긔긔",
    "점수": "",
    "격노": "147",
    "_originalRowNumber": 118
  },
  {
    "순위": "111",
    "길드": "NTR",
    "닉네임": "래시온",
    "점수": "61,427,923,675",
    "격노": "146",
    "_originalRowNumber": 119
  },
  {
    "순위": "112",
    "길드": "ARISE",
    "닉네임": "다이노스",
    "점수": "59,521,412,373",
    "격노": "146",
    "_originalRowNumber": 120
  },
  {
    "순위": "113",
    "길드": "NTR",
    "닉네임": "고려왕조태조샷건",
    "점수": "60,916,963,518",
    "격노": "145",
    "_originalRowNumber": 121
  },
  {
    "순위": "114",
    "길드": "ARISE",
    "닉네임": "교탐",
    "점수": "58,265,909,930",
    "격노": "145",
    "_originalRowNumber": 122
  },
  {
    "순위": "115",
    "길드": "미레이",
    "닉네임": "인생무상",
    "점수": "55,937,952,994",
    "격노": "144",
    "_originalRowNumber": 123
  },
  {
    "순위": "116",
    "길드": "NTR",
    "닉네임": "파머핑거",
    "점수": "55,055,409,655",
    "격노": "144",
    "_originalRowNumber": 124
  },
  {
    "순위": "117",
    "길드": "아이유",
    "닉네임": "깝진이",
    "점수": "",
    "격노": "144",
    "_originalRowNumber": 125
  },
  {
    "순위": "118",
    "길드": "NTR",
    "닉네임": "FeedBack",
    "점수": "50,812,797,597",
    "격노": "142",
    "_originalRowNumber": 126
  },
  {
    "순위": "119",
    "길드": "미레이",
    "닉네임": "woobin",
    "점수": "50,537,403,516",
    "격노": "141",
    "_originalRowNumber": 127
  },
  {
    "순위": "120",
    "길드": "NTR",
    "닉네임": "라키오라독니",
    "점수": "50,006,423,572",
    "격노": "141",
    "_originalRowNumber": 128
  },
  {
    "순위": "121",
    "길드": "NTR",
    "닉네임": "윤세은",
    "점수": "49,013,977,492",
    "격노": "141",
    "_originalRowNumber": 129
  },
  {
    "순위": "122",
    "길드": "NTR",
    "닉네임": "피넛칩쿠키",
    "점수": "50,211,146,509",
    "격노": "140",
    "_originalRowNumber": 130
  },
  {
    "순위": "123",
    "길드": "NTR",
    "닉네임": "다인",
    "점수": "49,377,718,096",
    "격노": "140",
    "_originalRowNumber": 131
  },
  {
    "순위": "124",
    "길드": "NTR",
    "닉네임": "탈세의품격",
    "점수": "48,390,429,711",
    "격노": "140",
    "_originalRowNumber": 132
  },
  {
    "순위": "125",
    "길드": "NTR",
    "닉네임": "dropbox",
    "점수": "51,240,380,394",
    "격노": "139",
    "_originalRowNumber": 133
  },
  {
    "순위": "126",
    "길드": "NTR",
    "닉네임": "성진우",
    "점수": "47,557,275,928",
    "격노": "139",
    "_originalRowNumber": 134
  },
  {
    "순위": "127",
    "길드": "NTR",
    "닉네임": "안똥배",
    "점수": "45,828,428,330",
    "격노": "139",
    "_originalRowNumber": 135
  },
  {
    "순위": "128",
    "길드": "ARISE",
    "닉네임": "큰사람",
    "점수": "47,564,581,833",
    "격노": "138",
    "_originalRowNumber": 136
  },
  {
    "순위": "129",
    "길드": "NTR",
    "닉네임": "개두술",
    "점수": "46,182,659,082",
    "격노": "138",
    "_originalRowNumber": 137
  },
  {
    "순위": "130",
    "길드": "NTR",
    "닉네임": "LocT",
    "점수": "44,105,040,389",
    "격노": "137",
    "_originalRowNumber": 138
  },
  {
    "순위": "131",
    "길드": "아이유",
    "닉네임": "라브",
    "점수": "",
    "격노": "137",
    "_originalRowNumber": 139
  },
  {
    "순위": "132",
    "길드": "NTR",
    "닉네임": "꼬맹E",
    "점수": "40,964,084,073",
    "격노": "136",
    "_originalRowNumber": 140
  },
  {
    "순위": "133",
    "길드": "NTR",
    "닉네임": "군단장",
    "점수": "40,427,248,548",
    "격노": "135",
    "_originalRowNumber": 141
  },
  {
    "순위": "134",
    "길드": "NTR",
    "닉네임": "Playgu",
    "점수": "40,334,706,034",
    "격노": "135",
    "_originalRowNumber": 142
  },
  {
    "순위": "135",
    "길드": "미레이",
    "닉네임": "네크로맨서",
    "점수": "39,936,785,585",
    "격노": "135",
    "_originalRowNumber": 143
  },
  {
    "순위": "136",
    "길드": "NTR",
    "닉네임": "독보",
    "점수": "39,659,643,953",
    "격노": "135",
    "_originalRowNumber": 144
  },
  {
    "순위": "137",
    "길드": "아이유",
    "닉네임": "피간지",
    "점수": "",
    "격노": "135",
    "_originalRowNumber": 145
  },
  {
    "순위": "138",
    "길드": "아이유",
    "닉네임": "수박같은호박",
    "점수": "",
    "격노": "135",
    "_originalRowNumber": 146
  },
  {
    "순위": "139",
    "길드": "아이유",
    "닉네임": "대가리꽃밭",
    "점수": "",
    "격노": "135",
    "_originalRowNumber": 147
  },
  {
    "순위": "140",
    "길드": "미레이",
    "닉네임": "아진",
    "점수": "39,458,154,640",
    "격노": "134",
    "_originalRowNumber": 148
  },
  {
    "순위": "141",
    "길드": "미레이",
    "닉네임": "화령",
    "점수": "39,343,933,376",
    "격노": "134",
    "_originalRowNumber": 149
  },
  {
    "순위": "142",
    "길드": "아이유",
    "닉네임": "괴개",
    "점수": "",
    "격노": "134",
    "_originalRowNumber": 150
  },
  {
    "순위": "143",
    "길드": "아이유",
    "닉네임": "화니",
    "점수": "",
    "격노": "134",
    "_originalRowNumber": 151
  },
  {
    "순위": "144",
    "길드": "아이유",
    "닉네임": "민니",
    "점수": "",
    "격노": "134",
    "_originalRowNumber": 152
  },
  {
    "순위": "145",
    "길드": "NTR",
    "닉네임": "돌돌이",
    "점수": "39,764,012,473",
    "격노": "133",
    "_originalRowNumber": 153
  },
  {
    "순위": "146",
    "길드": "미레이",
    "닉네임": "SuperRookie",
    "점수": "38,822,750,654",
    "격노": "133",
    "_originalRowNumber": 154
  },
  {
    "순위": "147",
    "길드": "NTR",
    "닉네임": "헬릉",
    "점수": "38,751,694,578",
    "격노": "133",
    "_originalRowNumber": 155
  },
  {
    "순위": "148",
    "길드": "NTR",
    "닉네임": "아까미",
    "점수": "37,532,836,825",
    "격노": "133",
    "_originalRowNumber": 156
  },
  {
    "순위": "149",
    "길드": "아이유",
    "닉네임": "azuretier",
    "점수": "",
    "격노": "133",
    "_originalRowNumber": 157
  },
  {
    "순위": "150",
    "길드": "NTR",
    "닉네임": "도마이",
    "점수": "36,265,250,536",
    "격노": "132",
    "_originalRowNumber": 158
  },
  {
    "순위": "151",
    "길드": "아이유",
    "닉네임": "포카칩",
    "점수": "",
    "격노": "132",
    "_originalRowNumber": 159
  },
  {
    "순위": "152",
    "길드": "아이유",
    "닉네임": "Hunter47940728",
    "점수": "",
    "격노": "131",
    "_originalRowNumber": 160
  },
  {
    "순위": "153",
    "길드": "아이유",
    "닉네임": "기등",
    "점수": "",
    "격노": "131",
    "_originalRowNumber": 161
  },
  {
    "순위": "154",
    "길드": "NTR",
    "닉네임": "윤쥰균",
    "점수": "33,911,201,484",
    "격노": "130",
    "_originalRowNumber": 162
  },
  {
    "순위": "155",
    "길드": "NTR",
    "닉네임": "JuNiX",
    "점수": "32,522,087,126",
    "격노": "129",
    "_originalRowNumber": 163
  },
  {
    "순위": "156",
    "길드": "미레이",
    "닉네임": "그리피아",
    "점수": "32,062,446,373",
    "격노": "129",
    "_originalRowNumber": 164
  },
  {
    "순위": "157",
    "길드": "미레이",
    "닉네임": "우렁이",
    "점수": "31,083,519,945",
    "격노": "128",
    "_originalRowNumber": 165
  },
  {
    "순위": "158",
    "길드": "NTR",
    "닉네임": "사랑감기에실려",
    "점수": "29,196,547,008",
    "격노": "127",
    "_originalRowNumber": 166
  },
  {
    "순위": "159",
    "길드": "미레이",
    "닉네임": "라이레스",
    "점수": "28,985,294,444",
    "격노": "127",
    "_originalRowNumber": 167
  },
  {
    "순위": "160",
    "길드": "아이유",
    "닉네임": "수압합격",
    "점수": "",
    "격노": "127",
    "_originalRowNumber": 168
  },
  {
    "순위": "161",
    "길드": "NTR",
    "닉네임": "비비츄",
    "점수": "27,503,319,605",
    "격노": "126",
    "_originalRowNumber": 169
  },
  {
    "순위": "162",
    "길드": "아이유",
    "닉네임": "아이유",
    "점수": "",
    "격노": "126",
    "_originalRowNumber": 170
  },
  {
    "순위": "163",
    "길드": "NTR",
    "닉네임": "Luap",
    "점수": "26,860,389,054",
    "격노": "125",
    "_originalRowNumber": 171
  },
  {
    "순위": "164",
    "길드": "아이유",
    "닉네임": "가진진",
    "점수": "",
    "격노": "125",
    "_originalRowNumber": 172
  },
  {
    "순위": "165",
    "길드": "NTR",
    "닉네임": "라디르",
    "점수": "25,855,676,915",
    "격노": "124",
    "_originalRowNumber": 173
  },
  {
    "순위": "166",
    "길드": "미레이",
    "닉네임": "대가리럭키비키",
    "점수": "25,109,567,116",
    "격노": "124",
    "_originalRowNumber": 174
  },
  {
    "순위": "167",
    "길드": "아이유",
    "닉네임": "무과금",
    "점수": "",
    "격노": "124",
    "_originalRowNumber": 175
  },
  {
    "순위": "168",
    "길드": "NTR",
    "닉네임": "RacerKim",
    "점수": "25,896,827,884",
    "격노": "123",
    "_originalRowNumber": 176
  },
  {
    "순위": "169",
    "길드": "NTR",
    "닉네임": "말포이",
    "점수": "24,789,593,770",
    "격노": "123",
    "_originalRowNumber": 177
  },
  {
    "순위": "170",
    "길드": "미레이",
    "닉네임": "올인클",
    "점수": "24,710,328,317",
    "격노": "123",
    "_originalRowNumber": 178
  },
  {
    "순위": "171",
    "길드": "NTR",
    "닉네임": "얼리성진우",
    "점수": "24,417,134,412",
    "격노": "123",
    "_originalRowNumber": 179
  },
  {
    "순위": "172",
    "길드": "아이유",
    "닉네임": "어비스",
    "점수": "",
    "격노": "123",
    "_originalRowNumber": 180
  },
  {
    "순위": "173",
    "길드": "아이유",
    "닉네임": "Zizou",
    "점수": "",
    "격노": "123",
    "_originalRowNumber": 181
  },
  {
    "순위": "174",
    "길드": "아이유",
    "닉네임": "깍까",
    "점수": "",
    "격노": "123",
    "_originalRowNumber": 182
  },
  {
    "순위": "175",
    "길드": "NTR",
    "닉네임": "ALA",
    "점수": "23,631,975,746",
    "격노": "122",
    "_originalRowNumber": 183
  },
  {
    "순위": "176",
    "길드": "NTR",
    "닉네임": "달빛",
    "점수": "23,313,498,154",
    "격노": "122",
    "_originalRowNumber": 184
  },
  {
    "순위": "177",
    "길드": "미레이",
    "닉네임": "메시",
    "점수": "23,188,047,803",
    "격노": "122",
    "_originalRowNumber": 185
  },
  {
    "순위": "178",
    "길드": "미레이",
    "닉네임": "NISIN",
    "점수": "22,808,566,846",
    "격노": "122",
    "_originalRowNumber": 186
  },
  {
    "순위": "179",
    "길드": "아이유",
    "닉네임": "성진우",
    "점수": "",
    "격노": "121",
    "_originalRowNumber": 187
  },
  {
    "순위": "180",
    "길드": "아이유",
    "닉네임": "베르제부브",
    "점수": "",
    "격노": "121",
    "_originalRowNumber": 188
  },
  {
    "순위": "181",
    "길드": "아이유",
    "닉네임": "멍청",
    "점수": "",
    "격노": "121",
    "_originalRowNumber": 189
  },
  {
    "순위": "182",
    "길드": "아이유",
    "닉네임": "NaDa",
    "점수": "",
    "격노": "119",
    "_originalRowNumber": 190
  },
  {
    "순위": "183",
    "길드": "아이유",
    "닉네임": "지성지수네",
    "점수": "",
    "격노": "119",
    "_originalRowNumber": 191
  },
  {
    "순위": "184",
    "길드": "NTR",
    "닉네임": "용탄",
    "점수": "19,567,421,131",
    "격노": "118",
    "_originalRowNumber": 192
  },
  {
    "순위": "185",
    "길드": "아이유",
    "닉네임": "한겨울",
    "점수": "",
    "격노": "118",
    "_originalRowNumber": 193
  },
  {
    "순위": "186",
    "길드": "아이유",
    "닉네임": "SUMIN",
    "점수": "",
    "격노": "118",
    "_originalRowNumber": 194
  },
  {
    "순위": "187",
    "길드": "미레이",
    "닉네임": "Value",
    "점수": "19,305,172,210",
    "격노": "117",
    "_originalRowNumber": 195
  },
  {
    "순위": "188",
    "길드": "아이유",
    "닉네임": "떵구리",
    "점수": "",
    "격노": "116",
    "_originalRowNumber": 196
  },
  {
    "순위": "189",
    "길드": "미레이",
    "닉네임": "Hunter36921823",
    "점수": "17,653,902,963",
    "격노": "115",
    "_originalRowNumber": 197
  },
  {
    "순위": "190",
    "길드": "미레이",
    "닉네임": "Hongga",
    "점수": "17,186,304,030",
    "격노": "115",
    "_originalRowNumber": 198
  },
  {
    "순위": "191",
    "길드": "미레이",
    "닉네임": "멋쟁이복",
    "점수": "17,084,629,728",
    "격노": "115",
    "_originalRowNumber": 199
  },
  {
    "순위": "192",
    "길드": "아이유",
    "닉네임": "대관람차",
    "점수": "",
    "격노": "115",
    "_originalRowNumber": 200
  },
  {
    "순위": "193",
    "길드": "NTR",
    "닉네임": "열심히삽니다",
    "점수": "17,101,712,782",
    "격노": "114",
    "_originalRowNumber": 201
  },
  {
    "순위": "194",
    "길드": "미레이",
    "닉네임": "LAWLITE",
    "점수": "15,675,705,076",
    "격노": "114",
    "_originalRowNumber": 202
  },
  {
    "순위": "195",
    "길드": "미레이",
    "닉네임": "히말",
    "점수": "16,052,000,601",
    "격노": "113",
    "_originalRowNumber": 203
  },
  {
    "순위": "196",
    "길드": "아이유",
    "닉네임": "SMASH",
    "점수": "",
    "격노": "113",
    "_originalRowNumber": 204
  },
  {
    "순위": "197",
    "길드": "미레이",
    "닉네임": "래삐",
    "점수": "14,868,675,067",
    "격노": "112",
    "_originalRowNumber": 205
  },
  {
    "순위": "198",
    "길드": "아이유",
    "닉네임": "김기돌A",
    "점수": "",
    "격노": "112",
    "_originalRowNumber": 206
  },
  {
    "순위": "199",
    "길드": "아이유",
    "닉네임": "Epilogue",
    "점수": "",
    "격노": "112",
    "_originalRowNumber": 207
  },
  {
    "순위": "200",
    "길드": "아이유",
    "닉네임": "터키쉬앙고라",
    "점수": "",
    "격노": "111",
    "_originalRowNumber": 208
  },
  {
    "순위": "201",
    "길드": "미레이",
    "닉네임": "eaglejump",
    "점수": "13,271,249,212",
    "격노": "110",
    "_originalRowNumber": 209
  },
  {
    "순위": "202",
    "길드": "미레이",
    "닉네임": "똥자루",
    "점수": "12,780,336,142",
    "격노": "109",
    "_originalRowNumber": 210
  },
  {
    "순위": "203",
    "길드": "미레이",
    "닉네임": "Lyooon",
    "점수": "12,054,545,573",
    "격노": "108",
    "_originalRowNumber": 211
  },
  {
    "순위": "204",
    "길드": "아이유",
    "닉네임": "레비",
    "점수": "",
    "격노": "108",
    "_originalRowNumber": 212
  },
  {
    "순위": "205",
    "길드": "아이유",
    "닉네임": "HASEUL",
    "점수": "",
    "격노": "108",
    "_originalRowNumber": 213
  },
  {
    "순위": "206",
    "길드": "미레이",
    "닉네임": "플레이어",
    "점수": "11,463,918,731",
    "격노": "107",
    "_originalRowNumber": 214
  },
  {
    "순위": "207",
    "길드": "미레이",
    "닉네임": "나그네",
    "점수": "10,411,138,788",
    "격노": "105",
    "_originalRowNumber": 215
  },
  {
    "순위": "208",
    "길드": "미레이",
    "닉네임": "초코칩쿠키",
    "점수": "10,358,915,325",
    "격노": "105",
    "_originalRowNumber": 216
  },
  {
    "순위": "209",
    "길드": "미레이",
    "닉네임": "뱅구",
    "점수": "10,350,218,591",
    "격노": "104",
    "_originalRowNumber": 217
  },
  {
    "순위": "210",
    "길드": "미레이",
    "닉네임": "유슬",
    "점수": "10,061,362,255",
    "격노": "104",
    "_originalRowNumber": 218
  },
  {
    "순위": "211",
    "길드": "아이유",
    "닉네임": "떡뻥",
    "점수": "",
    "격노": "101",
    "_originalRowNumber": 219
  },
  {
    "순위": "212",
    "길드": "미레이",
    "닉네임": "꼬리",
    "점수": "9,157,258,514",
    "격노": "100",
    "_originalRowNumber": 220
  },
  {
    "순위": "213",
    "길드": "아이유",
    "닉네임": "풍류",
    "점수": "",
    "격노": "99",
    "_originalRowNumber": 221
  },
  {
    "순위": "214",
    "길드": "미레이",
    "닉네임": "우타당",
    "점수": "7,999,905,482",
    "격노": "98",
    "_originalRowNumber": 222
  },
  {
    "순위": "215",
    "길드": "미레이",
    "닉네임": "ETA",
    "점수": "8,093,159,573",
    "격노": "97",
    "_originalRowNumber": 223
  },
  {
    "순위": "216",
    "길드": "아이유",
    "닉네임": "신화",
    "점수": "",
    "격노": "97",
    "_originalRowNumber": 224
  },
  {
    "순위": "217",
    "길드": "미레이",
    "닉네임": "시보니",
    "점수": "7,466,984,705",
    "격노": "94",
    "_originalRowNumber": 225
  },
  {
    "순위": "218",
    "길드": "미레이",
    "닉네임": "제라",
    "점수": "6,959,207,567",
    "격노": "93",
    "_originalRowNumber": 226
  },
  {
    "순위": "219",
    "길드": "아이유",
    "닉네임": "Kercy",
    "점수": "",
    "격노": "93",
    "_originalRowNumber": 227
  },
  {
    "순위": "220",
    "길드": "아이유",
    "닉네임": "잉명",
    "점수": "",
    "격노": "92",
    "_originalRowNumber": 228
  },
  {
    "순위": "221",
    "길드": "미레이",
    "닉네임": "팔라딘",
    "점수": "4,978,765,597",
    "격노": "79",
    "_originalRowNumber": 229
  },
  {
    "순위": "222",
    "길드": "ARISE",
    "닉네임": "Hodon",
    "점수": "36,021,629,526",
    "격노": "76",
    "_originalRowNumber": 230
  },
  {
    "순위": "223",
    "길드": "아이유",
    "닉네임": "웹프",
    "점수": "",
    "격노": "75",
    "_originalRowNumber": 231
  },
  {
    "순위": "224",
    "길드": "미레이",
    "닉네임": "parsa",
    "점수": "2,997,923,833",
    "격노": "70",
    "_originalRowNumber": 232
  },
  {
    "순위": "225",
    "길드": "미레이",
    "닉네임": "Solo",
    "점수": "2,744,721,055",
    "격노": "69",
    "_originalRowNumber": 233
  },
  {
    "순위": "226",
    "길드": "미레이",
    "닉네임": "Son",
    "점수": "3,786,522,378",
    "격노": "48",
    "_originalRowNumber": 234
  },
  {
    "순위": "227",
    "길드": "NTR",
    "닉네임": "비련적",
    "점수": "",
    "격노": "",
    "_originalRowNumber": 235
  },
  {
    "순위": "228",
    "길드": "NTR",
    "닉네임": "BB",
    "점수": "",
    "격노": "",
    "_originalRowNumber": 236
  },
  {
    "순위": "229",
    "길드": "NTR",
    "닉네임": "장군",
    "점수": "",
    "격노": "",
    "_originalRowNumber": 237
  },
  {
    "순위": "230",
    "길드": "미레이",
    "닉네임": "이몰리스",
    "점수": "",
    "격노": "",
    "_originalRowNumber": 238
  },
  {
    "순위": "231",
    "길드": "미레이",
    "닉네임": "코코",
    "점수": "",
    "격노": "",
    "_originalRowNumber": 239
  },
  {
    "순위": "232",
    "길드": "미레이",
    "닉네임": "Hunter207327",
    "점수": "",
    "격노": "",
    "_originalRowNumber": 240
  },
  {
    "순위": "233",
    "길드": "미레이",
    "닉네임": "대파장사",
    "점수": "",
    "격노": "",
    "_originalRowNumber": 241
  },
  {
    "순위": "234",
    "길드": "미레이",
    "닉네임": "스위치",
    "점수": "",
    "격노": "",
    "_originalRowNumber": 242
  },
  {
    "순위": "235",
    "길드": "미레이",
    "닉네임": "꼬맹이집사",
    "점수": "",
    "격노": "",
    "_originalRowNumber": 243
  },
  {
    "순위": "236",
    "길드": "미레이",
    "닉네임": "탑알바",
    "점수": "",
    "격노": "",
    "_originalRowNumber": 244
  },
  {
    "순위": "237",
    "길드": "미레이",
    "닉네임": "Papihustla",
    "점수": "",
    "격노": "",
    "_originalRowNumber": 245
  },
  {
    "순위": "238",
    "길드": "미레이",
    "닉네임": "마카티",
    "점수": "",
    "격노": "",
    "_originalRowNumber": 246
  },
  {
    "순위": "239",
    "길드": "아이유",
    "닉네임": "메론",
    "점수": "",
    "격노": "",
    "_originalRowNumber": 247
  },
  {
    "순위": "240",
    "길드": "아이유",
    "닉네임": "망고아빠",
    "점수": "",
    "격노": "",
    "_originalRowNumber": 248
  },
  {
    "순위": "241",
    "길드": "아이유",
    "닉네임": "난나또오",
    "점수": "",
    "격노": "",
    "_originalRowNumber": 249
  },
  {
    "순위": "242",
    "길드": "242",
    "닉네임": "",
    "점수": "",
    "격노": "",
    "_originalRowNumber": 250
  },
  {
    "순위": "243",
    "길드": "243",
    "닉네임": "",
    "점수": "",
    "격노": "",
    "_originalRowNumber": 251
  },
  {
    "순위": "244",
    "길드": "244",
    "닉네임": "",
    "점수": "",
    "격노": "",
    "_originalRowNumber": 252
  },
  {
    "순위": "245",
    "길드": "245",
    "닉네임": "",
    "점수": "",
    "격노": "",
    "_originalRowNumber": 253
  },
  {
    "순위": "246",
    "길드": "246",
    "닉네임": "",
    "점수": "",
    "격노": "",
    "_originalRowNumber": 254
  },
  {
    "순위": "247",
    "길드": "247",
    "닉네임": "",
    "점수": "",
    "격노": "",
    "_originalRowNumber": 255
  },
  {
    "순위": "248",
    "길드": "",
    "닉네임": "",
    "점수": "",
    "격노": "",
    "_originalRowNumber": 256
  },
  {
    "순위": "249",
    "길드": "",
    "닉네임": "",
    "점수": "",
    "격노": "",
    "_originalRowNumber": 257
  }
]