[
  {
    "인게임_닉": "SHIN",
    "태그": "BVVWO",
    "38주차": "140",
    "39주차": "135",
    "40주차": "138",
    "41주차": "147",
    "42주차": "147",
    "43주차": "146",
    "44주차": "150",
    "_originalRowNumber": 9
  },
  {
    "인게임_닉": "🇬🇴🇷🇦🇳🇮",
    "태그": "27TLSO",
    "38주차": "138",
    "39주차": "136",
    "40주차": "139",
    "41주차": "147",
    "42주차": "150",
    "43주차": "156",
    "44주차": "154",
    "_originalRowNumber": 10
  },
  {
    "인게임_닉": "Machineboy空",
    "태그": "LRIAOO",
    "38주차": "140",
    "39주차": "138",
    "40주차": "139",
    "41주차": "146",
    "42주차": "144",
    "43주차": "149",
    "44주차": "147",
    "_originalRowNumber": 11
  },
  {
    "인게임_닉": "무야",
    "태그": "QHZPP9",
    "38주차": "136",
    "39주차": "139",
    "40주차": "140",
    "41주차": "145",
    "42주차": "150",
    "43주차": "155",
    "44주차": "155",
    "_originalRowNumber": 12
  },
  {
    "인게임_닉": "OhReung",
    "태그": "7KD50F",
    "38주차": "129",
    "39주차": "134",
    "40주차": "135",
    "41주차": "140",
    "42주차": "139",
    "43주차": "145",
    "44주차": "148",
    "_originalRowNumber": 13
  },
  {
    "인게임_닉": "rock",
    "태그": "L97FGK",
    "38주차": "127",
    "39주차": "133",
    "40주차": "134",
    "41주차": "138",
    "42주차": "140",
    "43주차": "145",
    "44주차": "146",
    "_originalRowNumber": 14
  },
  {
    "인게임_닉": "하츄",
    "태그": "QH1NHD",
    "38주차": "131",
    "39주차": "133",
    "40주차": "134",
    "41주차": "135",
    "42주차": "141",
    "43주차": "147",
    "44주차": "145",
    "_originalRowNumber": 15
  },
  {
    "인게임_닉": "shamblez",
    "태그": "QB8V9O",
    "38주차": "128",
    "39주차": "132",
    "40주차": "134",
    "41주차": "139",
    "42주차": "102",
    "43주차": "148",
    "44주차": "150",
    "_originalRowNumber": 16
  },
  {
    "인게임_닉": "김소진",
    "태그": "GLPR35",
    "38주차": "133",
    "39주차": "134",
    "40주차": "135",
    "41주차": "143",
    "42주차": "144",
    "43주차": "147",
    "44주차": "148",
    "_originalRowNumber": 17
  },
  {
    "인게임_닉": "Goo",
    "태그": "8I2N6R",
    "38주차": "128",
    "39주차": "130",
    "40주차": "133",
    "41주차": "139",
    "42주차": "140",
    "43주차": "145",
    "44주차": "146",
    "_originalRowNumber": 18
  },
  {
    "인게임_닉": "베티",
    "태그": "GK2GU",
    "38주차": "130",
    "39주차": "134",
    "40주차": "135",
    "41주차": "142",
    "42주차": "141",
    "43주차": "148",
    "44주차": "148",
    "_originalRowNumber": 19
  },
  {
    "인게임_닉": "포레누아",
    "태그": "8QXTMO",
    "38주차": "108",
    "39주차": "125",
    "40주차": "131",
    "41주차": "133",
    "42주차": "136",
    "43주차": "138",
    "44주차": "143",
    "_originalRowNumber": 20
  },
  {
    "인게임_닉": "Dark",
    "태그": "T6MS8K",
    "38주차": "126",
    "39주차": "133",
    "40주차": "134",
    "41주차": "140",
    "42주차": "140",
    "43주차": "147",
    "44주차": "149",
    "_originalRowNumber": 21
  },
  {
    "인게임_닉": "RUBY",
    "태그": "KUM9FQ",
    "38주차": "132",
    "39주차": "132",
    "40주차": "135",
    "41주차": "139",
    "42주차": "140",
    "43주차": "144",
    "44주차": "144",
    "_originalRowNumber": 22
  },
  {
    "인게임_닉": "쭈니",
    "태그": "JC2BX7",
    "38주차": "130",
    "39주차": "134",
    "40주차": "135",
    "41주차": "143",
    "42주차": "143",
    "43주차": "148",
    "44주차": "150",
    "_originalRowNumber": 23
  },
  {
    "인게임_닉": "Need",
    "태그": "MABM1T",
    "38주차": "130",
    "39주차": "129",
    "40주차": "130",
    "41주차": "133",
    "42주차": "140",
    "43주차": "143",
    "44주차": "143",
    "_originalRowNumber": 24
  },
  {
    "인게임_닉": "연어",
    "태그": "71VCU",
    "38주차": "124",
    "39주차": "129",
    "40주차": "131",
    "41주차": "134",
    "42주차": "138",
    "43주차": "140",
    "44주차": "142",
    "_originalRowNumber": 25
  },
  {
    "인게임_닉": "GOLD",
    "태그": "T7DPIK",
    "38주차": "124",
    "39주차": "129",
    "40주차": "132",
    "41주차": "137",
    "42주차": "140",
    "43주차": "147",
    "44주차": "144",
    "_originalRowNumber": 26
  },
  {
    "인게임_닉": "우주최강스타킹",
    "태그": "2E64FK",
    "38주차": "125",
    "39주차": "138",
    "40주차": "136",
    "41주차": "142",
    "42주차": "147",
    "43주차": "152",
    "44주차": "152",
    "_originalRowNumber": 27
  },
  {
    "인게임_닉": "절두",
    "태그": "J69VOF",
    "38주차": "128",
    "39주차": "133",
    "40주차": "135",
    "41주차": "141",
    "42주차": "146",
    "43주차": "150",
    "44주차": "149",
    "_originalRowNumber": 28
  },
  {
    "인게임_닉": "stony",
    "태그": "GDTRUF",
    "38주차": "127",
    "39주차": "134",
    "40주차": "134",
    "41주차": "139",
    "42주차": "142",
    "43주차": "145",
    "44주차": "147",
    "_originalRowNumber": 29
  },
  {
    "인게임_닉": "전투경찰순경",
    "태그": "OW0VVF",
    "38주차": "125",
    "39주차": "128",
    "40주차": "132",
    "41주차": "137",
    "42주차": "138",
    "43주차": "141",
    "44주차": "144",
    "_originalRowNumber": 30
  },
  {
    "인게임_닉": "똥맨",
    "태그": "E1DC7R",
    "38주차": "128",
    "39주차": "131",
    "40주차": "134",
    "41주차": "134",
    "42주차": "140",
    "43주차": "145",
    "44주차": "144",
    "_originalRowNumber": 31
  },
  {
    "인게임_닉": "띵박",
    "태그": "FAVHC",
    "38주차": "126",
    "39주차": "130",
    "40주차": "131",
    "41주차": "132",
    "42주차": "136",
    "43주차": "140",
    "44주차": "143",
    "_originalRowNumber": 32
  },
  {
    "인게임_닉": "오리옌테이션",
    "태그": "MUFWGQ",
    "38주차": "129",
    "39주차": "133",
    "40주차": "134",
    "41주차": "140",
    "42주차": "144",
    "43주차": "146",
    "44주차": "148",
    "_originalRowNumber": 33
  },
  {
    "인게임_닉": "도리도리메모보리캥거루",
    "태그": "ETDDSR",
    "38주차": "132",
    "39주차": "136",
    "40주차": "135",
    "41주차": "145",
    "42주차": "143",
    "43주차": "149",
    "44주차": "151",
    "_originalRowNumber": 34
  },
  {
    "인게임_닉": "오렌지밀크",
    "태그": "BUU9R",
    "38주차": "125",
    "39주차": "128",
    "40주차": "130",
    "41주차": "135",
    "42주차": "138",
    "43주차": "143",
    "44주차": "140",
    "_originalRowNumber": 35
  },
  {
    "인게임_닉": "여미",
    "태그": "L0P990",
    "38주차": "121",
    "39주차": "127",
    "40주차": "130",
    "41주차": "136",
    "42주차": "137",
    "43주차": "140",
    "44주차": "141",
    "_originalRowNumber": 36
  },
  {
    "인게임_닉": "그르르",
    "태그": "KNWVZ7",
    "38주차": "130",
    "39주차": "134",
    "40주차": "136",
    "41주차": "144",
    "42주차": "146",
    "43주차": "151",
    "44주차": "154",
    "_originalRowNumber": 37
  },
  {
    "인게임_닉": "AYAAN",
    "태그": "BKY43G",
    "38주차": "132",
    "39주차": "132",
    "40주차": "136",
    "41주차": "143",
    "42주차": "142",
    "43주차": "149",
    "44주차": "150",
    "_originalRowNumber": 38
  },
  {
    "인게임_닉": "아야러아",
    "태그": "VQWOXT",
    "38주차": "126",
    "39주차": "130",
    "40주차": "131",
    "41주차": "135",
    "42주차": "137",
    "43주차": "139",
    "44주차": "139",
    "_originalRowNumber": 39
  },
  {
    "인게임_닉": "소월",
    "태그": "BXI6ER",
    "38주차": "127",
    "39주차": "131",
    "40주차": "134",
    "41주차": "140",
    "42주차": "140",
    "43주차": "144",
    "44주차": "145",
    "_originalRowNumber": 40
  },
  {
    "인게임_닉": "뉴이",
    "태그": "VY1BE0",
    "38주차": "130",
    "39주차": "134",
    "40주차": "136",
    "41주차": "144",
    "42주차": "143",
    "43주차": "146",
    "44주차": "148",
    "_originalRowNumber": 41
  },
  {
    "인게임_닉": "국민학교졸업생",
    "태그": "O40A7T",
    "38주차": "126",
    "39주차": "125",
    "40주차": "129",
    "41주차": "136",
    "42주차": "139",
    "43주차": "142",
    "44주차": "144",
    "_originalRowNumber": 42
  },
  {
    "인게임_닉": "Shubel",
    "태그": "KIPVB9",
    "38주차": "126",
    "39주차": "130",
    "40주차": "132",
    "41주차": "139",
    "42주차": "138",
    "43주차": "145",
    "44주차": "144",
    "_originalRowNumber": 43
  },
  {
    "인게임_닉": "Dawn",
    "태그": "ORLYO1",
    "38주차": "132",
    "39주차": "132",
    "40주차": "132",
    "41주차": "138",
    "42주차": "142",
    "43주차": "145",
    "44주차": "143",
    "_originalRowNumber": 44
  },
  {
    "인게임_닉": "묵직한주먹",
    "태그": "LK352T",
    "38주차": "133",
    "39주차": "132",
    "40주차": "134",
    "41주차": "142",
    "42주차": "143",
    "43주차": "149",
    "44주차": "150",
    "_originalRowNumber": 45
  },
  {
    "인게임_닉": "휘또르",
    "태그": "S4NIF1",
    "38주차": "128",
    "39주차": "127",
    "40주차": "129",
    "41주차": "134",
    "42주차": "138",
    "43주차": "140",
    "44주차": "141",
    "_originalRowNumber": 46
  },
  {
    "인게임_닉": "달마시안",
    "태그": "7FEVS",
    "38주차": "127",
    "39주차": "129",
    "40주차": "134",
    "41주차": "136",
    "42주차": "140",
    "43주차": "144",
    "44주차": "146",
    "_originalRowNumber": 47
  },
  {
    "인게임_닉": "44khz",
    "태그": "EZJYOI",
    "38주차": "122",
    "39주차": "130",
    "40주차": "131",
    "41주차": "137",
    "42주차": "139",
    "43주차": "142",
    "44주차": "146",
    "_originalRowNumber": 48
  },
  {
    "인게임_닉": "귀신",
    "태그": "MVYDJF",
    "38주차": "127",
    "39주차": "125",
    "40주차": "131",
    "41주차": "140",
    "42주차": "140",
    "43주차": "146",
    "44주차": "147",
    "_originalRowNumber": 49
  },
  {
    "인게임_닉": "허픽",
    "태그": "FRPN4F",
    "38주차": "124",
    "39주차": "131",
    "40주차": "133",
    "41주차": "140",
    "42주차": "142",
    "43주차": "145",
    "44주차": "146",
    "_originalRowNumber": 50
  },
  {
    "인게임_닉": "YF",
    "태그": "E9IBOF",
    "38주차": "",
    "39주차": "134",
    "40주차": "131",
    "41주차": "138",
    "42주차": "138",
    "43주차": "141",
    "44주차": "139",
    "_originalRowNumber": 51
  },
  {
    "인게임_닉": "우주최강귀요미",
    "태그": "2DMC4F",
    "38주차": "",
    "39주차": "122",
    "40주차": "133",
    "41주차": "142",
    "42주차": "140",
    "43주차": "147",
    "44주차": "148",
    "_originalRowNumber": 52
  },
  {
    "인게임_닉": "푸쉬팝",
    "태그": "QHMED1",
    "38주차": "",
    "39주차": "",
    "40주차": "128",
    "41주차": "135",
    "42주차": "135",
    "43주차": "141",
    "44주차": "144",
    "_originalRowNumber": 53
  },
  {
    "인게임_닉": "AwPSoul",
    "태그": "OZM6A0",
    "38주차": "",
    "39주차": "",
    "40주차": "",
    "41주차": "134",
    "42주차": "141",
    "43주차": "145",
    "44주차": "148",
    "_originalRowNumber": 54
  },
  {
    "인게임_닉": "lo",
    "태그": "8MCVY",
    "38주차": "",
    "39주차": "",
    "40주차": "",
    "41주차": "136",
    "42주차": "145",
    "43주차": "147",
    "44주차": "145",
    "_originalRowNumber": 55
  },
  {
    "인게임_닉": "성수호",
    "태그": "QUTWP9",
    "38주차": "",
    "39주차": "",
    "40주차": "",
    "41주차": "",
    "42주차": "",
    "43주차": "152",
    "44주차": "144",
    "_originalRowNumber": 56
  },
  {
    "인게임_닉": "Imnm",
    "태그": "O8S4Y",
    "38주차": "",
    "39주차": "",
    "40주차": "",
    "41주차": "",
    "42주차": "",
    "43주차": "142",
    "44주차": "144",
    "_originalRowNumber": 57
  },
  {
    "인게임_닉": "둘영",
    "태그": "L9V9DT",
    "38주차": "",
    "39주차": "",
    "40주차": "",
    "41주차": "",
    "42주차": "",
    "43주차": "140",
    "44주차": "145",
    "_originalRowNumber": 58
  }
]